pyrecord/__init__.py
pyrecord/exceptions.py
pyrecord/_validation/__init__.py
pyrecord/_validation/_generic_utils.py
pyrecord/_validation/instance_validators.py
pyrecord/_validation/type_validators.py
pyrecord-1.0.1.dist-info/DESCRIPTION.rst
pyrecord-1.0.1.dist-info/METADATA
pyrecord-1.0.1.dist-info/RECORD
pyrecord-1.0.1.dist-info/WHEEL
pyrecord-1.0.1.dist-info/metadata.json
pyrecord-1.0.1.dist-info/top_level.txt
