Metadata-Version: 1.1
Name: pyrecord
Version: 1.0.1
Summary: Pythonic Record Types
Home-page: https://pythonhosted.org/pyrecord/
Author: Gustavo Narea
Author-email: me@gustavonarea.net
License: Apache License, Version 2.0
Keywords: record type struct data structure
Platform: UNKNOWN
Classifier: Development Status :: 5 - Production/Stable
Classifier: Intended Audience :: Developers
Classifier: License :: OSI Approved :: Apache Software License
Classifier: Natural Language :: English
Classifier: Operating System :: OS Independent
Classifier: Programming Language :: Python
Classifier: Topic :: Software Development :: Libraries
